cssformatter.py
format.py
z_format-0.7.0.dist-info/DESCRIPTION.rst
z_format-0.7.0.dist-info/METADATA
z_format-0.7.0.dist-info/RECORD
z_format-0.7.0.dist-info/WHEEL
z_format-0.7.0.dist-info/entry_points.txt
z_format-0.7.0.dist-info/metadata.json
z_format-0.7.0.dist-info/top_level.txt
