Metadata-Version: 2.0
Name: z-format
Version: 0.7.0
Summary: A CLI formatter for JavaScript and CSS (beautify or minimize).
Home-page: https://github.com/joshsziegler/z-format
Author: Josh Ziegler
Author-email: josh.s.ziegler@gmail.com
License: MIT
Platform: UNKNOWN
Requires-Python: >=3.4
Requires-Dist: jsbeautifier (>=1.6)
Requires-Dist: jsmin (>=2.2)
